incrementalstats/__init__.py
incrementalstats/covariance_correlation.py
incrementalstats/mean_var.py
incrementalstats/welcht.py
incrementalstats-1.0.4.dist-info/licenses/LICENSE
incrementalstats-1.0.4.dist-info/METADATA
incrementalstats-1.0.4.dist-info/WHEEL
incrementalstats-1.0.4.dist-info/top_level.txt
incrementalstats-1.0.4.dist-info/RECORD
